python_utilisation/__init__.py
python_utilisation/read.py
python_utilisation/read_csv.py
python_utilisation/utils_enum.py
python_utilisation/utils_list.py
python_utilisation-0.0.14.dist-info/LICENSE
python_utilisation-0.0.14.dist-info/METADATA
python_utilisation-0.0.14.dist-info/WHEEL
python_utilisation-0.0.14.dist-info/top_level.txt
python_utilisation-0.0.14.dist-info/RECORD
