Metadata-Version: 2.1
Name: python-utilisation
Version: 0.0.14
Summary: make python easier
Home-page: https://github.com/Djeevs-Jean/
Author: Jean-Yves Badette
Author-email: jeanyvesbadette@gmail.com
License: MIT
Keywords: python-utilisation,python-utils,python,utilisation
Classifier: Programming Language :: Python :: 3
Classifier: License :: OSI Approved :: MIT License
Classifier: Operating System :: OS Independent
License-File: LICENSE
